{
    "ZZ": {
        "A_chb": -0.09289383888244629,
        "u_A_chb": 0.0016105082368337144,
        "A_chbox": 0.12125968933105469,
        "u_A_chbox": 0.0,
        "A_chdd": 0.015926361083984375,
        "u_A_chdd": 0.0001460009659995543,
        "A_che": -0.09319782257080078,
        "u_A_che": 2.676241912918526e-05,
        "A_chj3": -0.05601048469543457,
        "u_A_chj3": 0.0001538400384903014,
        "A_chl1": 0.13434886932373047,
        "u_A_chl1": 8.279683758824033e-05,
        "A_chl3": -0.17699003219604492,
        "u_A_chl3": 0.00020232594517908693,
        "A_chq1": -0.015234947204589844,
        "u_A_chq1": 3.705089156131757e-05,
        "A_chq3": -0.015234947204589844,
        "u_A_chq3": 3.705089156131757e-05,
        "A_chu": -0.010704994201660156,
        "u_A_chu": 4.3735352344141345e-05,
        "A_chwb": -0.019979476928710938,
        "u_A_chwb": 0.0008573477074443318,
        "A_cll1": 0.1377105712890625,
        "u_A_cll1": 0.00013011845490817843,
        "B_chb_2": 0.4112720489501953,
        "u_B_chb_2": 0.014666134356717776,
        "B_chb_chwb": -0.25331974029541016,
        "u_B_chb_chwb": 0.01757680236870437,
        "B_chbox_chl3": -0.01728534698486328,
        "u_B_chbox_chl3": 0.00029200193199910854,
        "B_chdd_chb": -0.04589557647705078,
        "u_B_chdd_chb": 0.0013274584681582503,
        "B_chdd_che": 0.012516975402832031,
        "u_B_chdd_che": 0.0013591950238932824,
        "B_chdd_chl1": 0.011920928955078125,
        "u_B_chdd_chl1": 0.0017192608239479015,
        "B_chdd_chl3": 0.011324882507324219,
        "u_B_chdd_chl3": 0.0016858739404357612,
        "B_chdd_chw": 0.045299530029296875,
        "u_B_chdd_chw": 0.00029200193199910854,
        "B_chdd_chwb": 0.010132789611816406,
        "u_B_chdd_chwb": 0.0012615925364802315,
        "B_che_cll1": -0.010132789611816406,
        "u_B_che_cll1": 0.0009973764735866494,
        "B_chl1_2": 0.01430511474609375,
        "u_B_chl1_2": 0.0032340669551493015,
        "B_chl3_2": 0.016689300537109375,
        "u_B_chl3_2": 0.003615796777749801,
        "B_chl3_che": 0.020265579223632812,
        "u_B_chl3_che": 0.0013274584681582503,
        "B_chl3_cll1": -0.022649765014648438,
        "u_B_chl3_cll1": 0.0016345154286387072,
        "B_chw_2": 0.11205673217773438,
        "u_B_chw_2": 0.0013058723390225557,
        "B_chw_chb": -0.017881393432617188,
        "u_B_chw_chb": 0.008995365848500005,
        "B_chw_chwb": -0.16927719116210938,
        "u_B_chw_chwb": 0.004732473669357111,
        "B_chwb_2": 0.12636184692382812,
        "u_B_chwb_2": 0.006615847075229457,
        "B_chwb_che": 0.010132789611816406,
        "u_B_chwb_che": 0.0008760057959973258
    },
    "gamgam": {
        "A_chb": -40.149,
        "A_chbox": 0.121224,
        "A_chd": -0.241643,
        "A_chl3": -0.363754,
        "A_chw": -13.0861,
        "A_chwb": 22.3044,
        "A_cll1": 0.181877,
        "A_ctbre": -2.15072,
        "A_cthre": 0.0344664,
        "A_ctwre": -1.15159,
        "A_cw": -0.946266,
        "B_chb_2": 402.985,
        "B_chd_2": 0.0145979,
        "B_chl3_2": 0.0330792,
        "B_chw_2": 42.8117,
        "B_chwb_2": 124.372,
        "B_ctbre_2": 1.1564,
        "B_ctwre_2": 0.331537,
        "B_cw_2": 0.223855,
        "B_chb_chbox": -2.43352,
        "B_chb_chd": 4.85087,
        "B_chb_chl3": 7.30217,
        "B_chb_chw": 262.697,
        "B_chb_chwb": -447.75,
        "B_chb_cll1": -3.65108,
        "B_chb_ctbre": 43.1746,
        "B_chb_cthre": -0.691895,
        "B_chb_ctwre": 23.1175,
        "B_chb_cw": 18.9958,
        "B_chbox_chd": -0.0146465,
        "B_chbox_chl3": -0.0220479,
        "B_chbox_chw": -0.793178,
        "B_chbox_chwb": 1.35192,
        "B_chbox_cll1": 0.0110239,
        "B_chbox_ctbre": -0.13036,
        "B_chbox_ctwre": -0.0698001,
        "B_chbox_cw": -0.0573552,
        "B_chd_chl3": 0.0439493,
        "B_chd_chw": 1.58109,
        "B_chd_chwb": -2.69485,
        "B_chd_cll1": -0.0219746,
        "B_chd_ctbre": 0.259853,
        "B_chd_ctwre": 0.139136,
        "B_chd_cw": 0.114329,
        "B_chl3_chw": 2.38006,
        "B_chl3_chwb": -4.05665,
        "B_chl3_cll1": -0.0330792,
        "B_chl3_ctbre": 0.391166,
        "B_chl3_ctwre": 0.209447,
        "B_chl3_cw": 0.172104,
        "B_chw_chwb": -145.939,
        "B_chw_cll1": -1.19003,
        "B_chw_ctbre": 14.0723,
        "B_chw_cthre": -0.225516,
        "B_chw_ctwre": 7.5349,
        "B_chw_cw": 6.19148,
        "B_chwb_cll1": 2.02833,
        "B_chwb_ctbre": -23.9853,
        "B_chwb_cthre": 0.384376,
        "B_chwb_ctwre": -12.8427,
        "B_chwb_cw": -10.553,
        "B_cll1_ctbre": -0.195583,
        "B_cll1_ctwre": -0.104723,
        "B_cll1_cw": -0.0860519,
        "B_ctbre_cthre": -0.0370638,
        "B_ctbre_ctwre": 1.23837,
        "B_ctbre_cw": 1.01758,
        "B_cthre_ctwre": -0.0198455,
        "B_cthre_cw": -0.0163072,
        "B_ctwre_cw": 0.544853
    },
    "bb": {
        "A_chbox": 0.1212481150408084,
        "u_A_chbox": 0.0,
        "A_chdd": -0.030312087057909054,
        "u_A_chdd": 0.0,
        "A_cbhre": -6.521383598911775,
        "u_A_cbhre": 0.0,
        "A_chl3": -0.12124815390594634,
        "u_A_chl3": 6.9390871739186175e-06,
        "A_cll1": 0.06062409638554217,
        "u_A_cll1": 1.73096089815817e-06,
        "B_cbhim_2": 10.660707345511074,
        "u_B_cbhim_2": 0.0,
        "B_cbhre_2": 10.632110376991838,
        "u_B_cbhre_2": 0.0,
        "B_chbox_cbhre": -0.3953525068013991,
        "u_B_chbox_cbhre": 0.0,
        "B_chdd_cbhre": 0.0988382432957637,
        "u_B_chdd_cbhre": 0.0,
        "B_cbhre_chl3": 0.3953525068013991,
        "u_B_cbhre_chl3": 0.0,
        "B_cbhre_cll1": -0.19767617567042364,
        "u_B_cbhre_cll1": 0.0
    },
    "WW": {
        "A_chbox": 0.12124809023601613,
        "u_A_chbox": 1.3554632528858088e-05,
        "A_chdd": -0.030965202177738925,
        "u_A_chdd": 0.0003736205375895942,
        "A_chj3": -0.07712507795510672,
        "u_A_chj3": 0.0005792405202369567,
        "A_chl3": -0.15111966167320678,
        "u_A_chl3": 0.0006750616346518034,
        "A_chw": -0.08801473775465972,
        "u_A_chw": 0.0003921627962102089,
        "A_cll1": 0.12393100975310588,
        "u_A_cll1": 0.000435350039432312,
        "B_chb_2": 0.018812310359774598,
        "u_B_chb_2": 5.955437692076245e-05,
        "B_chb_chwb": 0.023728868660598177,
        "u_B_chb_chwb": 0.00012561192621055812,
        "B_chbtil_2": 0.017631122670134374,
        "u_B_chbtil_2": 5.627506353230664e-05,
        "B_chbtil_chwbtil": 0.023490463805808402,
        "u_B_chbtil_chwbtil": 0.00012217485083141616,
        "B_chl3_cll1": -0.011946008764434048,
        "u_B_chl3_cll1": 7.335948705862236e-05,
        "B_chw_2": 0.021532293021239705,
        "u_B_chw_2": 6.910955873143112e-05,
        "B_chw_chb": -0.037509752925877764,
        "u_B_chw_chb": 0.00016851237206905043,
        "B_chw_chwb": -0.023611833550065024,
        "u_B_chw_chwb": 0.00012403919065032178,
        "B_chwtil_2": 0.01873645426961422,
        "u_B_chwtil_2": 5.9644390400372003e-05,
        "B_chwtil_chbtil": -0.03517988729952319,
        "u_B_chwtil_chbtil": 0.00015434690617777643,
        "B_chwtil_chwbtil": -0.023408105765062855,
        "u_B_chwtil_chwbtil": 0.00011334965788604068
    },
    "tautau": {
        "A_chbox": 0.12124810927612287,
        "u_A_chbox": 7.5735582698857025e-06,
        "A_chdd": -0.030312046612131504,
        "u_A_chdd": 0.0,
        "A_cehre": -0.12124814786232443,
        "u_A_cehre": 3.872313297704572e-06,
        "A_chl3": -0.12124814786232443,
        "u_A_chl3": 3.872313297704572e-06,
        "A_cll1": 0.06062397746565829,
        "u_A_cll1": 7.530134556922009e-06
    },
    "mumu": {
        "A_chbox": 0.12124818799114975,
        "u_A_chbox": 0.0,
        "A_chdd": -0.030312014299883377,
        "u_A_chdd": 2.379422578153748e-06,
        "A_cehre": -0.1212480789981362,
        "u_A_cehre": 2.3661251118051852e-05,
        "A_chl3": -0.1212480789981362,
        "u_A_chl3": 2.3661251118051852e-05,
        "A_cll1": 0.0606240394990681,
        "u_A_cll1": 0.0
    },
    "Zgam": {
        "A_chb": -15.4736,
        "A_chl3": -0.363636,
        "A_chq1": 0.0177033,
        "A_chq3": -0.0177033,
        "A_cht": 0.0177033,
        "A_chw": 14.5795,
        "A_chwb": -15.7794,
        "A_cll1": 0.181818,
        "A_ctbre": 0.0977673,
        "A_ctwre": -0.711921,
        "A_cw": -0.922778,
        "B_chb_2": 59.8577,
        "B_chl3_2": 0.0330579,
        "B_chw_2": 53.1407,
        "B_chwb_2": 62.247,
        "B_ctwre_2": 0.126708,
        "B_cw_2": 0.21288,
        "B_chb_chl3": 2.81337,
        "B_chb_chq1": -0.136967,
        "B_chb_chq3": 0.136967,
        "B_chb_cht": -0.136967,
        "B_chb_chw": -112.799,
        "B_chb_chwb": 122.081,
        "B_chb_cll1": -1.40669,
        "B_chb_ctbre": -0.756404,
        "B_chb_cthre": -0.0557492,
        "B_chb_ctwre": 5.50797,
        "B_chb_cw": 7.13933,
        "B_chl3_chw": -2.65082,
        "B_chl3_chwb": 2.86897,
        "B_chl3_cll1": -0.0330579,
        "B_chl3_ctbre": -0.0177759,
        "B_chl3_ctwre": 0.12944,
        "B_chl3_cw": 0.167778,
        "B_chq1_chw": 0.129053,
        "B_chq1_chwb": -0.139674,
        "B_chq3_chw": -0.129053,
        "B_chq3_chwb": 0.139674,
        "B_cht_chw": 0.129053,
        "B_cht_chwb": -0.139674,
        "B_chw_chwb": -115.028,
        "B_chw_cll1": 1.32541,
        "B_chw_ctbre": 0.712701,
        "B_chw_cthre": 0.0525282,
        "B_chw_ctwre": -5.18974,
        "B_chw_cw": -6.72684,
        "B_chwb_cll1": -1.43449,
        "B_chwb_ctbre": -0.771352,
        "B_chwb_cthre": -0.056851,
        "B_chwb_ctwre": 5.61683,
        "B_chwb_cw": 7.28042,
        "B_cll1_ctwre": -0.0647201,
        "B_cll1_cw": -0.0838889,
        "B_ctbre_ctwre": -0.0348013,
        "B_ctbre_cw": -0.0451088,
        "B_ctwre_cw": 0.328472
    },
    "cc": {
        "A_chbox": 0.121248076543697,
        "u_A_chbox": 0.0,
        "A_chdd": -0.030312043795620438,
        "u_A_chdd": 2.9406519705146946e-06,
        "A_cuhre": -0.1212480272243046,
        "u_A_cuhre": 0.0,
        "A_chl3": -0.1212480272243046,
        "u_A_chl3": 0.0,
        "A_cll1": 0.0606240382718485,
        "u_A_cll1": 9.871655541521966e-06
    },
    "gluglu": {
        "A_chg": 39.34896452737338,
        "u_A_chg": 0.0036136598569541825,
        "B_chgtil_2": 387.08519581710067,
        "u_B_chgtil_2": 0.0,
        "B_chg_2": 387.08519581710067,
        "u_B_chg_2": 0.0
    },
    "tot": {
        "A_cbhre": -3.8088150367339573,
        "A_chb": -0.11774443348228512,
        "A_chbox": 0.111094283433403,
        "A_chdd": -0.026404145059498056,
        "A_chg": 3.2321440588070733,
        "A_chl3": -0.14154198253734226,
        "A_chw": -0.025550148767896373,
        "A_chwb": 0.025344581352730065,
        "A_cll1": 0.07134550085869427,
        "B_cbhim_2": 6.242545538123147,
        "B_cbhim_chb": 3.3510912804758477,
        "B_cbhim_chg": 0.014628421046515452,
        "B_cbhim_chw": 3.3500869203424903,
        "B_cbhim_chwb": 3.351048456001841,
        "B_cbhre_2": 6.22621399834023,
        "B_cbhre_chl3": 0.23092237845299146,
        "B_cbhre_cll1": -0.11546102662935359,
        "B_chb_2": 1.0212057849486498,
        "B_chb_cbhre": 3.342522454467392,
        "B_chb_chd": 0.011036311030384272,
        "B_chb_chl3": 0.021276106259909756,
        "B_chb_chw": 0.42466410726423676,
        "B_chb_chwb": -0.8322553869975238,
        "B_chb_cll1": -0.010628074555237026,
        "B_chb_ctbre": 0.09715364878520405,
        "B_chb_ctwre": 0.06111778696348864,
        "B_chb_cw": 0.054241816439559574,
        "B_chbox_cbhre": -0.23090568894729965,
        "B_chbtil_2": 0.011073807708891499,
        "B_chbtil_cbhim": 3.3511836329294016,
        "B_chbtil_cbhre": 3.342718467041639,
        "B_chbtil_chg": -1.9403787529141718,
        "B_chdd_cbhre": 0.05773553134319613,
        "B_chg_2": 36.08012882940807,
        "B_chg_cbgre": -0.013265722812744157,
        "B_chg_cbhre": -0.2398682763695252,
        "B_chg_chb": -1.9405225414513168,
        "B_chg_chw": -1.940455801866151,
        "B_chg_chwb": -1.9403220513966928,
        "B_chgtil_2": 36.789955552717714,
        "B_chgtil_cbgim": -0.014443708107001352,
        "B_chgtil_cbhim": -0.24447798174123503,
        "B_chgtil_cbhre": -0.016595938300865233,
        "B_chgtil_chb": -2.656860443801512,
        "B_chgtil_chbtil": -2.656987954391056,
        "B_chgtil_chw": -2.6578789007231043,
        "B_chgtil_chwb": -2.6561173554935094,
        "B_chgtil_chwbtil": -2.656102705340668,
        "B_chgtil_chwtil": -2.6570644607447824,
        "B_chw_2": 0.1851187104182335,
        "B_chw_cbhre": 3.341555450081759,
        "B_chw_chwb": -0.5171435048897725,
        "B_chw_ctbre": 0.03314207242151862,
        "B_chwb_2": 0.3827505596435743,
        "B_chwb_cbhre": 3.342560745111354,
        "B_chwb_ctbre": -0.055806251282768574,
        "B_chwb_ctwre": -0.020603491854327555,
        "B_chwb_cw": -0.01282979767715212,
        "B_chwbtil_cbhim": 3.3510615343607566,
        "B_chwbtil_cbhre": 3.3425531353061406,
        "B_chwbtil_chg": -1.9403074012438517,
        "B_chwtil_cbhim": 3.3503472853927523,
        "B_chwtil_cbhre": 3.341836678697281,
        "B_chwtil_chg": -1.9404552592678976,
        "u_A_cbhre": 0.0001056745724508178,
        "u_A_chb": 1.0147176901146234e-05,
        "u_A_chbox": 2.7970303863269623e-06,
        "u_A_chdd": 4.545715888105106e-05,
        "u_A_chg": 0.0009228754689976675,
        "u_A_chl3": 9.665160542956318e-05,
        "u_A_chw": 6.2492631209787e-05,
        "u_A_chwb": 4.872736821665181e-06,
        "u_A_cll1": 6.270238882590454e-05,
        "u_B_cbhim_2": 0.01328331480900777,
        "u_B_cbhim_chb": 0.026367907814640806,
        "u_B_cbhim_chg": 0.014722949945654332,
        "u_B_cbhim_chw": 0.026369026786247196,
        "u_B_cbhim_chwb": 0.02633790701877546,
        "u_B_cbhre_2": 0.01333116701390985,
        "u_B_cbhre_chl3": 1.8991051055397575e-05,
        "u_B_cbhre_cll1": 9.453460310809879e-06,
        "u_B_chb_2": 1.7751651848669297e-05,
        "u_B_chb_cbhre": 0.02639220130474713,
        "u_B_chb_chd": 2.575491050452275e-05,
        "u_B_chb_chl3": 3.0516314145272055e-05,
        "u_B_chb_chw": 0.0,
        "u_B_chb_chwb": 2.702993435135781e-05,
        "u_B_chb_cll1": 2.56031005082551e-05,
        "u_B_chb_ctbre": 0.0,
        "u_B_chb_ctwre": 0.0,
        "u_B_chb_cw": 0.0,
        "u_B_chbox_cbhre": 6.4064258182917576e-06,
        "u_B_chbtil_2": 1.7112840452170856e-05,
        "u_B_chbtil_cbhim": 0.026400114341287678,
        "u_B_chbtil_cbhre": 0.02640730917798766,
        "u_B_chbtil_chg": 4.154731555870219,
        "u_B_chdd_cbhre": 1.1238287156918522e-05,
        "u_B_chg_2": 4.154710498868562,
        "u_B_chg_cbgre": 0.013010202824059083,
        "u_B_chg_cbhre": 0.23614224261772826,
        "u_B_chg_chb": 4.15473155681966,
        "u_B_chg_chw": 4.15473155188581,
        "u_B_chg_chwb": 4.15473155365596,
        "u_B_chgtil_2": 4.863630032954914,
        "u_B_chgtil_cbgim": 0.014269116919541117,
        "u_B_chgtil_cbhim": 0.24295821319257593,
        "u_B_chgtil_cbhre": 0.0169720252320657,
        "u_B_chgtil_chb": 4.863656060115826,
        "u_B_chgtil_chbtil": 4.863656067738421,
        "u_B_chgtil_chw": 4.863655987144911,
        "u_B_chgtil_chwb": 4.863656023190989,
        "u_B_chgtil_chwbtil": 4.863656023679299,
        "u_B_chgtil_chwtil": 4.863656023778757,
        "u_B_chw_2": 9.050329912985551e-06,
        "u_B_chw_cbhre": 0.026367688732727653,
        "u_B_chw_chwb": 1.8186235084810188e-05,
        "u_B_chw_ctbre": 0.0,
        "u_B_chwb_2": 5.748347957614279e-06,
        "u_B_chwb_cbhre": 0.02649052789294373,
        "u_B_chwb_ctbre": 0.0,
        "u_B_chwb_ctwre": 0.0,
        "u_B_chwb_cw": 0.0,
        "u_B_chwbtil_cbhim": 0.026337908827162727,
        "u_B_chwbtil_cbhre": 0.026366507951876502,
        "u_B_chwbtil_chg": 4.154731553461103,
        "u_B_chwtil_cbhim": 0.02634791511891983,
        "u_B_chwtil_cbhre": 0.02637650639110261,
        "u_B_chwtil_chg": 4.154731552870521
    }
}
